{
	"status_led": {
		"led_gpio":2,
		"invert_gpio":true
	},
	"separate_accessories":true,
	"lights":[
		{
			"light_gpio":16,
			"invert_light_gpio":false,
			"led_gpio":13,
			"invert_led_gpio":true,
			"button_gpio":12,
			"invert_button_gpio":false,
			"is_dimmer":true,
			"is_remote":false,
			"is_hidden":true,
			"remote_cmd":null
		},
		{
			"light_gpio":5,
			"invert_light_gpio":true,
			"led_gpio":4,
			"invert_led_gpio":false,
			"button_gpio":14,
			"invert_button_gpio":true,
			"is_dimmer":false,
			"is_remote":true,
			"is_hidden":false,
			"remote_cmd":{"host":"http://device_ip_address:5556/characteristic","method":"PUT","payload":{"characteristics":[{"aid":1,"iid":9,"value":"ON"},{"aid":1,"iid":9,"value":"BRIGHTNESS"}]}}
		}
	]
}